logtron/__init__.py
logtron/autodiscover.py
logtron/config/__init__.py
logtron/config/discover_config.py
logtron/formatters/__init__.py
logtron/formatters/json_formatter.py
logtron/handlers/__init__.py
logtron/handlers/console.py
logtron/util/__init__.py
logtron/util/flatten_dict.py
logtron/util/merge_dict.py
logtron/util/parse_env.py
logtron-0.1.15.dist-info/LICENSE
logtron-0.1.15.dist-info/WHEEL
logtron-0.1.15.dist-info/METADATA
logtron-0.1.15.dist-info/RECORD
